Workbook

Sheet Company Overview
A1: Investor Name | B1: Investment Amount | C1: Ownership % | D1: Profit Share % | E1: Notes
A2: Md Rabiul Islam | B2: 20000 | C2: 0.5 | D2: 0.5
A3: Shuvo | B3: 90000 | C3: 0.25 | D3: 0.25
A4: rakib | B4: 30000 | C4: 0.25 | D4: 0.25

Sheet Stock Management
A1: Date | B1: Category | C1: Model | D1: Color | E1: Size | F1: Opening Stock | G1: Production Qty | H1: Sold Qty | I1: Returned Qty | J1: Current Stock | K1: Production Cost/Unit | L1: Total Stock Value
B2: Belt | J2: =E2+F2-G2+H2 -> 0 | L2: =I2*J2 -> 0
J3: =E3+F3-G3+H3 -> 0 | L3: =I3*J3 -> 0
J4: =E4+F4-G4+H4 -> 0 | L4: =I4*J4 -> 0
J5: =E5+F5-G5+H5 -> 0 | L5: =I5*J5 -> 0
J6: =E6+F6-G6+H6 -> 0 | L6: =I6*J6 -> 0
J7: =E7+F7-G7+H7 -> 0 | L7: =I7*J7 -> 0
J8: =E8+F8-G8+H8 -> 0 | L8: =I8*J8 -> 0
J9: =E9+F9-G9+H9 -> 0 | L9: =I9*J9 -> 0
J10: =E10+F10-G10+H10 -> 0 | L10: =I10*J10 -> 0
J11: =E11+F11-G11+H11 -> 0 | L11: =I11*J11 -> 0
J12: =E12+F12-G12+H12 -> 0 | L12: =I12*J12 -> 0
J13: =E13+F13-G13+H13 -> 0 | L13: =I13*J13 -> 0
J14: =E14+F14-G14+H14 -> 0 | L14: =I14*J14 -> 0
... J301: =E301+F301-G301+H301 -> 0 | L301: =I301*J301 -> 0

Sheet Office Expenses
A1: Date | B1: Category | C1: Description | D1: Amount | E1: Column1 | F1: Column2

Sheet Sales & Profit
A1: Date | B1: Invoice No | C1: Customer Name | D1: Customer Mobile | E1: Product Model | F1: Qty | G1: Selling Price | H1: Total Sale | I1: Production Cost/Unit | J1: Courier Cost | K1: Facebook Ads Cost | L1: Packaging Cost | M1: Total Cost | N1: Net Profit/Loss | O1: Payment Status | P1: Return Courier Fee (Customer) | Q1: Return Courier Fee (Company)
H2: =E2*F2 -> 0 | M2: =E2*(H2+I2+J2+K2) -> 0 | N2: =G2-L2+P2-Q2 -> 0
H3: =E3*F3 -> 0 | M3: =E3*(H3+I3+J3+K3) -> 0 | N3: =G3-L3+P3-Q3 -> 0
H4: =E4*F4 -> 0 | M4: =E4*(H4+I4+J4+K4) -> 0 | N4: =G4-L4+P4-Q4 -> 0
H5: =E5*F5 -> 0 | M5: =E5*(H5+I5+J5+K5) -> 0 | N5: =G5-L5+P5-Q5 -> 0
H6: =E6*F6 -> 0 | M6: =E6*(H6+I6+J6+K6) -> 0 | N6: =G6-L6+P6-Q6 -> 0
H7: =E7*F7 -> 0 | M7: =E7*(H7+I7+J7+K7) -> 0 | N7: =G7-L7+P7-Q7 -> 0
H8: =E8*F8 -> 0 | M8: =E8*(H8+I8+J8+K8) -> 0 | N8: =G8-L8+P8-Q8 -> 0
H9: =E9*F9 -> 0 | M9: =E9*(H9+I9+J9+K9) -> 0 | N9: =G9-L9+P9-Q9 -> 0
H10: =E10*F10 -> 0 | M10: =E10*(H10+I10+J10+K10) -> 0 | N10: =G10-L10+P10-Q10 -> 0
H11: =E11*F11 -> 0 | M11: =E11*(H11+I11+J11+K11) -> 0 | N11: =G11-L11+P11-Q11 -> 0
H12: =E12*F12 -> 0 | M12: =E12*(H12+I12+J12+K12) -> 0 | N12: =G12-L12+P12-Q12 -> 0
H13: =E13*F13 -> 0 | M13: =E13*(H13+I13+J13+K13) -> 0 | N13: =G13-L13+P13-Q13 -> 0
... H21: =E21*F21 -> 0 | M21: =E21*(H21+I21+J21+K21) -> 0 | N21: =G21-L21+P21-Q21 -> 0
H22: =E22*F22 -> 0 | M22: =E22*(H22+I22+J22+K22) -> 0 | N22: =G22-L22+P22-O23 -> 0
H23: =E23*F23 -> 0 | M23: =E23*(H23+I23+J23+K23) -> 0 | N23: =G23-L23+P23-Q23 -> 0
H24: =E24*F24 -> 0 | M24: =E24*(H24+I24+J24+K24) -> 0 | N24: =G24-L24+P24-Q24 -> 0
H25: =E25*F25 -> 0 | M25: =E25*(H25+I25+J25+K25) -> 0 | N25: =G25-L25+P25-Q25 -> 0
H26: =E26*F26 -> 0 | M26: =E26*(H26+I26+J26+K26) -> 0 | N26: =G26-L26+P26-Q26 -> 0
H27: =E27*F27 -> 0 | M27: =E27*(H27+I27+J27+K27) -> 0 | N27: =G27-L27+P27-Q27 -> 0
H28: =E28*F28 -> 0 | M28: =E28*(H28+I28+J28+K28) -> 0 | N28: =G28-L28+P28-Q28 -> 0
H29: =E29*F29 -> 0 | M29: =E29*(H29+I29+J29+K29) -> 0 | N29: =G29-L29+P29-Q29 -> 0
H30: =E30*F30 -> 0 | M30: =E30*(H30+I30+J30+K30) -> 0 | N30: =G30-L30+P30-Q30 -> 0
H31: =E31*F31 -> 0 | M31: =E31*(H31+I31+J31+K31) -> 0 | N31: =G31-L31+P31-Q31 -> 0
H32: =E32*F32 -> 0 | M32: =E32*(H32+I32+J32+K32) -> 0 | N32: =G32-L32+P32-Q32 -> 0
H33: =E33*F33 -> 0 | M33: =E33*(H33+I33+J33+K33) -> 0 | N33: =G33-L33+P33-Q33 -> 0
H34: =E34*F34 -> 0 | M34: =E34*(H34+I34+J34+K34) -> 0 | N34: =G34-L34+P34-Q34 -> 0
... H501: =E501*F501 -> 0 | M501: =E501*(H501+I501+J501+K501) -> 0 | N501: =G501-L501+P501-Q501 -> 0

Sheet Dashboard
A1: ZEEOX LEATHER BUSINESS DASHBOARD
A3: Total Sales | B3: =SUM('Sales & Profit'!G:G) -> 0
A4: Total Cost | B4: =SUM('Sales & Profit'!L:L) -> 0
A5: Net Profit | B5: =SUM('Sales & Profit'!M:M) -> 0
A6: Office Expenses | B6: =SUM('Office Expenses'!D:D) -> 0
A7: Total Stock Value | B7: =SUM('Stock Management'!K:K) -> 0
A8: Courier Cost | B8: =SUM('Courier Management'!I:I) -> 0

Sheet Courier Management
A1: Date | B1: Courier Name | C1: Tracking ID | D1: Customer | E1: Delivery Charge | F1: COD Charge | G1: Return Charge | H1: Status | I1: Net Courier Cost
I2: =E2+F2+G2 -> 0
I3: =E3+F3+G3 -> 0
I4: =E4+F4+G4 -> 0
I5: =E5+F5+G5 -> 0
I6: =E6+F6+G6 -> 0
I7: =E7+F7+G7 -> 0
I8: =E8+F8+G8 -> 0
I9: =E9+F9+G9 -> 0
I10: =E10+F10+G10 -> 0
I11: =E11+F11+G11 -> 0
I12: =E12+F12+G12 -> 0
I13: =E13+F13+G13 -> 0
... I301: =E301+F301+G301 -> 0

Sheet Production Management
A1: Date | B1: Model | C1: Material Cost | D1: Labor Cost | E1: Packaging Cost | F1: Other Cost | G1: Total Production Cost
G2: =SUM(C2:F2) -> 0
G3: =SUM(C3:F3) -> 0
G4: =SUM(C4:F4) -> 0
G5: =SUM(C5:F5) -> 0
G6: =SUM(C6:F6) -> 0
G7: =SUM(C7:F7) -> 0
G8: =SUM(C8:F8) -> 0
G9: =SUM(C9:F9) -> 0
G10: =SUM(C10:F10) -> 0
G11: =SUM(C11:F11) -> 0
G12: =SUM(C12:F12) -> 0
G13: =SUM(C13:F13) -> 0
... G301: =SUM(C301:F301) -> 0
